nice_list/__init__.py
nice_list-1.1.0.dist-info/DESCRIPTION.rst
nice_list-1.1.0.dist-info/METADATA
nice_list-1.1.0.dist-info/RECORD
nice_list-1.1.0.dist-info/WHEEL
nice_list-1.1.0.dist-info/metadata.json
nice_list-1.1.0.dist-info/top_level.txt
