Metadata-Version: 2.0
Name: nice-list
Version: 1.1.0
Summary: Pretty prints Python lists
Home-page: https://github.com/Fylipp/nice-list
Author: Philipp Ploder
Author-email: UNKNOWN
License: UNKNOWN
Keywords: lists
Platform: UNKNOWN
Classifier: Development Status :: 5 - Production/Stable
Classifier: License :: OSI Approved :: MIT License
Classifier: Programming Language :: Python :: 3
